[
    {
        "id": 1,
        "title": "The Lord of the Rings",
        "author": "J.R.R. Tolkien",
        "description": "The classic novel by J.R.R. Tolkien",
        "price": 0.00,
        "category": "Free",
        "img": "/LordOfTheRings.jpg"
    },
    {
        "id": 2,
        "title": "Pride and Prejudice",
        "author": "Jane Austen",
        "description": "A classic novel by Jane Austen",
        "price": 0.00,
        "category": "Free",
        "img": "/PrideAndPrejudice.jpeg"
    },
    {
        "id": 3,
        "title": "To Kill a Mockingbird",
        "author": "Harper Lee",
        "description": "A classic novel by Harper Lee",
        "price": 0.00,
        "category": "Free",
        "img": "/ToKillAMockingbird.jpeg"
    },
    {
        "id": 4,
        "title": "1984",
        "author": "George Orwell",
        "description": "A dystopian novel by George Orwell",
        "price": 55.00,
        "category": "Classic",
        "img": "/1984.jpg"
    },
    {
        "id": 5,
        "title": "The Great Gatsby",
        "author": "F. Scott Fitzgerald",
        "description": "A classic novel by F. Scott Fitzgerald",
        "price": 39.99,
        "category": "Classic",
        "img": "/TheGreatGatsby.jpg"
    },
    {
        "id": 6,
        "title": "The Catcher in the Rye",
        "author": "J.D. Salinger",
        "description": "A classic novel by J.D. Salinger",
        "price": 61.39,
        "category": "Crime",
        "img": "/TheCatcherInTheRye.jpg"
    },
    {
        "id": 7,
        "title": "The Hobbit",
        "author": "J.R.R. Tolkien",
        "description": "The classic novel by J.R.R. Tolkien",
        "price": 57.96,
        "category": "Fantasy",
        "img": "/TheHobbit.jpeg"
    },
    {
        "id": 8,
        "title": "The Alchemist",
        "author": "Paulo Coelho",
        "description": "A classic novel by Paulo Coelho",
        "price": 79.99,
        "category": "Fantasy",
        "img": "/TheAlchemist.jpeg"
    },
    {
        "id": 9,
        "title": "The Da Vinci Code",
        "author": "Dan Brown",
        "description": "A classic novel by Dan Brown",
        "price": 99.99,
        "category": "Crime",
        "img": "/TheDaVinciCode.jpg"
    },
    {
        "id": 10,
        "title": "The Hunger Games",
        "author": "Suzanne Collins",
        "description": "A dystopian novel by Suzanne Collins",
        "price": 105.00,
        "category": "Fantasy",
        "img": "/TheHungerGames.jpg"
    }
]